msda/__init__.py
msda/anamoly.py
msda/msda.py
msda/utils.py
msda-1.10.0.dist-info/LICENSE
msda-1.10.0.dist-info/METADATA
msda-1.10.0.dist-info/WHEEL
msda-1.10.0.dist-info/top_level.txt
msda-1.10.0.dist-info/RECORD
