Metadata-Version: 2.1
Name: msda
Version: 1.10.0
Summary: MSDA - An open source, low-code time-series multi-sensor data analysis, unsupervised feature selection, deep unsupervised anomaly detection & explainable time-series predictor library in Python.
Home-page: https://github.com/ajayarunachalam/msda
Author: Ajay Arunachalam
Author-email: ajay.arunachalam08@gmail.com
License: MIT
Platform: UNKNOWN
